saldor/__init__.py
saldor/saldor_client.py
saldor-0.0.14.dist-info/METADATA
saldor-0.0.14.dist-info/WHEEL
saldor-0.0.14.dist-info/RECORD
